webbot_ui_package_Umair_Shakoor/__init__.py
webbot_ui_package_Umair_Shakoor/ui_activity.py
webbot_ui_package_umair_shakoor-0.0.1.dist-info/METADATA
webbot_ui_package_umair_shakoor-0.0.1.dist-info/WHEEL
webbot_ui_package_umair_shakoor-0.0.1.dist-info/licenses/LICENSE
webbot_ui_package_umair_shakoor-0.0.1.dist-info/RECORD
