Metadata-Version: 2.3
Name: webbot_ui_package_Umair_Shakoor
Version: 0.0.1
Summary: Package for web bot creation
Project-URL: Homepage, https://pk.linkedin.com/in/umair-shakoor-2816a3185
Project-URL: Issues, https://pk.linkedin.com/in/umair-shakoor-2816a3185
Author-email: Umair Shakoor <atumair@gmail.com>
License-File: LICENSE
Classifier: License :: OSI Approved :: MIT License
Classifier: Operating System :: OS Independent
Classifier: Programming Language :: Python :: 3
Requires-Python: >=3.8
